Metadata-Version: 1.0
Name: dglushakov-icon
Version: 2.1.1
Summary: Icon AR2NS
Home-page: UNKNOWN
Author: UNKNOWN
Author-email: denis.glushakov@bk.ru
License: UNKNOWN
Platform: UNKNOWN
